{
    "version": "21.5.19",
    "license": "MIT",
    "persist": [
        "addons",
        "config",
        "init",
        "layout"
    ],
    "url": "https://github.com/tablacus/TablacusExplorer/releases/download/21.5.19/te210519.zip",
    "homepage": "https://tablacus.github.io/explorer_en.html",
    "hash": "7251bc568d31d17cf514dd1186fe5cc632c847c72ab3ed0b61ebc3f1eb160bc5",
    "shortcuts": [
        [
            "TE64.exe",
            "TablacusExplorer"
        ]
    ],
    "checkver": {
        "url": "https://github.com/tablacus/TablacusExplorer/releases",
        "re": "/(?<version>[\\d.]+)/te(?<file>[\\d]+).zip"
    },
    "autoupdate": {
        "url": "https://github.com/tablacus/TablacusExplorer/releases/download/$version/te$matchFile.zip"
    }
}
