{
    "version": "21.11.23",
    "license": "MIT",
    "persist": [
        "addons",
        "config",
        "init",
        "layout"
    ],
    "url": "https://github.com/tablacus/TablacusExplorer/releases/download/21.11.23/te211123.zip",
    "homepage": "https://tablacus.github.io/explorer_en.html",
    "hash": "899a0433d7db0d5adf3a116c765443b15adf761d5489f85d5dcd3f59fbd96f91",
    "shortcuts": [
        [
            "TE64.exe",
            "TablacusExplorer"
        ]
    ],
    "checkver": {
        "url": "https://github.com/tablacus/TablacusExplorer/releases",
        "re": "/(?<version>[\\d.]+)/te(?<file>[\\d]+).zip"
    },
    "autoupdate": {
        "url": "https://github.com/tablacus/TablacusExplorer/releases/download/$version/te$matchFile.zip"
    }
}
