{
    "version": "20.12.22",
    "license": "MIT",
    "persist": [
        "addons",
        "config",
        "init",
        "layout"
    ],
    "url": "https://github.com/tablacus/TablacusExplorer/releases/download/20.12.22/te201222.zip",
    "homepage": "https://tablacus.github.io/explorer_en.html",
    "hash": "65c39f0c940b6168a0b40babd5d6fe460553b838be087be7fb7813846a85926c",
    "shortcuts": [
        [
            "TE64.exe",
            "TablacusExplorer"
        ]
    ],
    "checkver": {
        "url": "https://github.com/tablacus/TablacusExplorer/releases",
        "re": "/(?<version>[\\d.]+)/te(?<file>[\\d]+).zip"
    },
    "autoupdate": {
        "url": "https://github.com/tablacus/TablacusExplorer/releases/download/$version/te$matchFile.zip"
    }
}
