{
    "version": "21.10.12",
    "license": "MIT",
    "persist": [
        "addons",
        "config",
        "init",
        "layout"
    ],
    "url": "https://github.com/tablacus/TablacusExplorer/releases/download/21.10.12/te211012.zip",
    "homepage": "https://tablacus.github.io/explorer_en.html",
    "hash": "39eee88a559ab9fc0d3ff62f497c3c085f8bef0d8b1745f986a817e284673843",
    "shortcuts": [
        [
            "TE64.exe",
            "TablacusExplorer"
        ]
    ],
    "checkver": {
        "url": "https://github.com/tablacus/TablacusExplorer/releases",
        "re": "/(?<version>[\\d.]+)/te(?<file>[\\d]+).zip"
    },
    "autoupdate": {
        "url": "https://github.com/tablacus/TablacusExplorer/releases/download/$version/te$matchFile.zip"
    }
}
