{
    "version": "20.8.9",
    "license": "MIT",
    "url": "https://github.com/tablacus/TablacusExplorer/releases/download/20.8.9/te200809.zip",
    "homepage": "https://tablacus.github.io/explorer_en.html",
    "hash": "36f8eef3b29efe97d9fb0620d50483aa9286b62fa1562ff77106cc647e8dcbbe",
    "shortcuts": [
        [
            "TE64.exe",
            "TablacusExplorer"
        ]
    ],
    "checkver": {
        "url": "https://github.com/tablacus/TablacusExplorer/releases",
        "re": "/(?<version>[\\d.]+)/te(?<file>[\\d]+).zip"
    },
    "autoupdate": {
        "url": "https://github.com/tablacus/TablacusExplorer/releases/download/$version/te$matchFile.zip"
    }
}
