{
    "version": "21.3.23",
    "license": "MIT",
    "persist": [
        "addons",
        "config",
        "init",
        "layout"
    ],
    "url": "https://github.com/tablacus/TablacusExplorer/releases/download/21.3.23/te210323.zip",
    "homepage": "https://tablacus.github.io/explorer_en.html",
    "hash": "9389264f55cc4830975c6869a2d63e735132414ffc966147fade37562dabc153",
    "shortcuts": [
        [
            "TE64.exe",
            "TablacusExplorer"
        ]
    ],
    "checkver": {
        "url": "https://github.com/tablacus/TablacusExplorer/releases",
        "re": "/(?<version>[\\d.]+)/te(?<file>[\\d]+).zip"
    },
    "autoupdate": {
        "url": "https://github.com/tablacus/TablacusExplorer/releases/download/$version/te$matchFile.zip"
    }
}
